thumbor_presets/__init__.py
thumbor_presets/app.py
thumbor_presets/handlers.py
thumbor_presets-0.1.3.dist-info/DESCRIPTION.rst
thumbor_presets-0.1.3.dist-info/METADATA
thumbor_presets-0.1.3.dist-info/RECORD
thumbor_presets-0.1.3.dist-info/WHEEL
thumbor_presets-0.1.3.dist-info/metadata.json
thumbor_presets-0.1.3.dist-info/top_level.txt
