Metadata-Version: 2.0
Name: thumbor-presets
Version: 0.1.3
Summary: thumbor-presets
Requires-Dist: thumbor
